qcloud_user/__init__.py
qcloud_user/qcloud_user.py
qcloud_user-1.0.17.data/scripts/qcloud_user.py
qcloud_user-1.0.17.dist-info/licenses/LICENSE.txt
qcloud_user-1.0.17.dist-info/METADATA
qcloud_user-1.0.17.dist-info/WHEEL
qcloud_user-1.0.17.dist-info/entry_points.txt
qcloud_user-1.0.17.dist-info/top_level.txt
qcloud_user-1.0.17.dist-info/RECORD
