Metadata-Version: 2.4
Name: qcloud_user
Version: 1.0.17
Summary: Q-Cloud CLI for users
Home-page: https://q-chem.com/explore/qcloud
Author-email: "Q-Chem Inc." <support@q-chem.com>
Project-URL: Homepage, https://q-chem.com
Keywords: qcloud,qchem,q-cloud,q-chem
Requires-Python: >=3.7
License-File: LICENSE.txt
Requires-Dist: boto3>=1.21.33
Requires-Dist: botocore>=1.24.33
Requires-Dist: demjson3>=3.0.6
Requires-Dist: paramiko>=3.1.0
Requires-Dist: pick>=2.2.0
Requires-Dist: PyYAML>=5.3
Requires-Dist: python-jose>=3.3.0
Requires-Dist: pyopenssl>=22.1.0
Requires-Dist: jose>=1.0
Requires-Dist: Requests==2.31.0
Dynamic: home-page
Dynamic: license-file
